{
  "noInheritance": {
    "type": "object",
    "description": "Add the name of the services here that you don't want to inherit from the previous service version. Ex: { 'cats': ['find']}",
    "minProperties": 1,
    "patternProperties": {
      "^.*$": {
        "allOf": [
          {
            "description": "The array of operations that you don't want to inherit from the previous operations",
            "type": "array",
            "items": {
              "type": "string"
            }
          }
        ]
      }
    },
    "additionalProperties": false
  },
  "definitions": {
    "type": "object"
  }
}
